ariadne_codegen_field_fix/__init__.py
ariadne_codegen_field_fix-0.1.0.dist-info/METADATA
ariadne_codegen_field_fix-0.1.0.dist-info/WHEEL
ariadne_codegen_field_fix-0.1.0.dist-info/RECORD
