Metadata-Version: 2.3
Name: ariadne-codegen-field-fix
Version: 0.1.0
Summary: 
Author: Ewen Lorimer
Author-email: dev@ewenlorimer.org
Requires-Python: >=3.9,<4
Classifier: Programming Language :: Python :: 3
Classifier: Programming Language :: Python :: 3.9
Classifier: Programming Language :: Python :: 3.10
Classifier: Programming Language :: Python :: 3.11
Classifier: Programming Language :: Python :: 3.12
Classifier: Programming Language :: Python :: 3.13
Requires-Dist: ariadne-codegen (>=0.15.2,<0.16.0)
